{
    "status": "success",
    "count": 150,
    "data": [
        {
            "id": 653,
            "name": "Future Pioneer High-Powered Toy - Creative & Educational Play for Kids",
            "url": "future-pioneer-high-powered",
            "brand_id": "0",
            "sku": "KCPR1653",
            "price": 550,
            "mrp": 699,
            "pprice": 250,
            "category": "Toys, Toys: Bikes & Cars",
            "stock": 1,
            "in_stock": true,
            "image": "https:\/\/d1s4zcjwkikclq.cloudfront.net\/main_prod_images\/KCPR1653\/1681547557.jpeg",
            "emoji": "\u2728",
            "discount_percentage": 21.32
        },
        {
            "id": 649,
            "name": "GLOBUS 404 with Money Box Desk & Table Top Political World Globe",
            "url": "globus-404-with-money-box-desk-table-top-political-world-globe",
            "brand_id": "0",
            "sku": "KCPR1649",
            "price": 270,
            "mrp": 300,
            "pprice": 140,
            "category": "Stationery, Toys",
            "stock": 4,
            "in_stock": true,
            "image": "https:\/\/d1s4zcjwkikclq.cloudfront.net\/main_prod_images\/KCPR1649\/1681545929.jpg",
            "emoji": "\u2728",
            "discount_percentage": 10
        },
        {
            "id": 822,
            "name": "Ganesh Ji Water Fountain \u2013 Elegant and Serene Water Feature for Your Home | Katyayani Creations",
            "url": "Ganesh-Ji-Water-Fountain",
            "brand_id": "0",
            "sku": "KCPR1822",
            "price": 1350,
            "mrp": 1500,
            "pprice": 500,
            "category": "Home & Decor, Home & Decor: Lamps, Mothers Day Store, WA Diwali Items",
            "stock": 1,
            "in_stock": true,
            "image": "https:\/\/d1s4zcjwkikclq.cloudfront.net\/main_prod_images\/KCPR1822\/16971159620.jpeg",
            "emoji": "\u2728",
            "discount_percentage": 10
        },
        {
            "id": 710,
            "name": "Gell Pen",
            "url": "gell-pen",
            "brand_id": "26",
            "sku": "KCPR1710",
            "price": 9,
            "mrp": 10,
            "pprice": 7,
            "category": "Stationery, Stationery: Pens",
            "stock": 252,
            "in_stock": true,
            "image": "https:\/\/d1s4zcjwkikclq.cloudfront.net\/main_prod_images\/KCPR1710\/1691906968.jpeg",
            "emoji": "\u2728",
            "discount_percentage": 10
        },
        {
            "id": 1199,
            "name": "Geltron Gell Pen",
            "url": "geltron-gell-pen",
            "brand_id": "42",
            "sku": "KCPR11199",
            "price": 9,
            "mrp": 10,
            "pprice": 6.5,
            "category": "Stationery: Pens, Stationery",
            "stock": 50,
            "in_stock": true,
            "image": "https:\/\/d1s4zcjwkikclq.cloudfront.net\/main_prod_images\/KCPR11199\/KCPR11199_17253909284.jpg",
            "emoji": "\u2728",
            "discount_percentage": 10
        },
        {
            "id": 33,
            "name": "Gift Wrapping Holographic Metallic Sheets",
            "url": "gift-wrapping-holographic-metallic-sheets",
            "brand_id": "0",
            "sku": "KCPR1033",
            "price": 10,
            "mrp": 15,
            "pprice": 2.5,
            "category": "Birthday Accessories, Stationery",
            "stock": 770,
            "in_stock": true,
            "image": "https:\/\/d1s4zcjwkikclq.cloudfront.net\/main_prod_images\/KCPR1033\/d2pjNaXQ.jpeg",
            "emoji": "\u2728",
            "discount_percentage": 33.33
        },
        {
            "id": 3,
            "name": "Gift Wrapping Paper",
            "url": "gift-wrapping-paper",
            "brand_id": "0",
            "sku": "KCPR1003",
            "price": 15,
            "mrp": 20,
            "pprice": 7,
            "category": "Birthday Accessories, Stationery",
            "stock": 758,
            "in_stock": true,
            "image": "https:\/\/d1s4zcjwkikclq.cloudfront.net\/main_prod_images\/KCPR1003\/G04gSczJ.jpeg",
            "emoji": "\u2728",
            "discount_percentage": 25
        },
        {
            "id": 543,
            "name": "Giftec Lavender Aroma Oil, Diffuser Set",
            "url": "giftec-lavender-aroma-oil-diffuser-set",
            "brand_id": "0",
            "sku": "KCPR1543",
            "price": 180,
            "mrp": 300,
            "pprice": 60,
            "category": "Home & Decor",
            "stock": 7,
            "in_stock": true,
            "image": "https:\/\/d1s4zcjwkikclq.cloudfront.net\/main_prod_images\/KCPR1543\/1673428370.jpeg",
            "emoji": "\u2728",
            "discount_percentage": 40
        },
        {
            "id": 1017,
            "name": "Gifting Moments",
            "url": "gifting-moments",
            "brand_id": "31",
            "sku": "KCPR11017",
            "price": 848,
            "mrp": 999,
            "pprice": 1,
            "category": "Gift Packs",
            "stock": 100,
            "in_stock": true,
            "image": "https:\/\/d1s4zcjwkikclq.cloudfront.net\/main_prod_images\/KCPR11017\/KCPR11017_17125760041.jpeg",
            "emoji": "\u2728",
            "discount_percentage": 15.12
        },
        {
            "id": 534,
            "name": "Girl Pretty Doll",
            "url": "girl-pretty-doll",
            "brand_id": "0",
            "sku": "KCPR1534",
            "price": 450,
            "mrp": 500,
            "pprice": 210,
            "category": "Toys, Toys: Dolls & Houses",
            "stock": 1,
            "in_stock": true,
            "image": "https:\/\/d1s4zcjwkikclq.cloudfront.net\/main_prod_images\/KCPR1534\/1673428918.jpeg",
            "emoji": "\u2728",
            "discount_percentage": 10
        },
        {
            "id": 121,
            "name": "Girls Pop it Pen for Kids",
            "url": "girls-pop-it-pen-for-kids",
            "brand_id": "0",
            "sku": "KCPR1121",
            "price": 20,
            "mrp": 20,
            "pprice": 10,
            "category": "Stationery: Pens, Stationery",
            "stock": 4,
            "in_stock": true,
            "image": "https:\/\/d1s4zcjwkikclq.cloudfront.net\/main_prod_images\/KCPR1121\/1662133445.jpg",
            "emoji": "\u2728",
            "discount_percentage": 0
        },
        {
            "id": 977,
            "name": "Glass Bottle",
            "url": "glass-bottle",
            "brand_id": "0",
            "sku": "KCPR1977",
            "price": 225,
            "mrp": 250,
            "pprice": 75,
            "category": "Home & Decor",
            "stock": 12,
            "in_stock": true,
            "image": "https:\/\/d1s4zcjwkikclq.cloudfront.net\/main_prod_images\/KCPR1977\/KCPR1977_17125776410.jpeg",
            "emoji": "\u2728",
            "discount_percentage": 10
        },
        {
            "id": 1486,
            "name": "Glass Bottle 52036",
            "url": "glass-bottle-52036",
            "brand_id": "0",
            "sku": "KCPR11486",
            "price": 112,
            "mrp": 124,
            "pprice": 62,
            "category": "Home & Decor",
            "stock": 12,
            "in_stock": true,
            "image": "https:\/\/d1s4zcjwkikclq.cloudfront.net\/main_prod_images\/KCPR11486\/KCPR11486_17572754710.jpg",
            "emoji": "\u2728",
            "discount_percentage": 9.68
        },
        {
            "id": 200,
            "name": "Glass Candle (Single)",
            "url": "glass-candle-single",
            "brand_id": "0",
            "sku": "KCPR1200",
            "price": 90,
            "mrp": 120,
            "pprice": 42,
            "category": "Diwali Items",
            "stock": 2,
            "in_stock": true,
            "image": "https:\/\/d1s4zcjwkikclq.cloudfront.net\/main_prod_images\/KCPR1200\/1663176974.jpeg",
            "emoji": "\u2728",
            "discount_percentage": 25
        },
        {
            "id": 1242,
            "name": "Glass Cups and Coffee Mug with Lids and Glass Straws Spill Proof Glass | 330 Ml",
            "url": "glass-cups-and-coffee-mug-with-lids-and-glass-straws-spill-proof-glass-330-ml",
            "brand_id": "0",
            "sku": "KCPR11242",
            "price": 128,
            "mrp": 200,
            "pprice": 85,
            "category": "Toys",
            "stock": 1,
            "in_stock": true,
            "image": "https:\/\/d1s4zcjwkikclq.cloudfront.net\/main_prod_images\/KCPR11242\/KCPR11242_17343322593.webp",
            "emoji": "\u2728",
            "discount_percentage": 36
        },
        {
            "id": 43,
            "name": "Glass LED Lamp Mataki 9 Inch - Elegant and Energy-Efficient Lighting Solution | Katyayani Creations",
            "url": "glass-led-lamp-mataki-9inch",
            "brand_id": "0",
            "sku": "KCPR1043",
            "price": 550,
            "mrp": 750,
            "pprice": 260,
            "category": "Home & Decor, Home & Decor: Lamps, WA Diwali Items",
            "stock": 1,
            "in_stock": true,
            "image": "https:\/\/d1s4zcjwkikclq.cloudfront.net\/main_prod_images\/KCPR1043\/gimUMc8C.jpeg",
            "emoji": "\u2728",
            "discount_percentage": 26.67
        },
        {
            "id": 160,
            "name": "Glass Transparent Gel Ink Pen",
            "url": "glass-transparent-gel-ink-pen",
            "brand_id": "9",
            "sku": "KCPR1160",
            "price": 9,
            "mrp": 10,
            "pprice": 10,
            "category": "Stationery: Pens, Stationery",
            "stock": 78,
            "in_stock": true,
            "image": "https:\/\/d1s4zcjwkikclq.cloudfront.net\/main_prod_images\/KCPR1160\/KCPR1160_17170102410.jpg",
            "emoji": "\u2728",
            "discount_percentage": 10
        },
        {
            "id": 216,
            "name": "Glitter Gel Pen (Set Of 10 Colors)",
            "url": "flair-glitter-gelpen-set-of-10-colors",
            "brand_id": "9",
            "sku": "KCPR1216",
            "price": 90,
            "mrp": 100,
            "pprice": 70,
            "category": "Stationery: Pens, Stationery",
            "stock": 2,
            "in_stock": true,
            "image": "https:\/\/d1s4zcjwkikclq.cloudfront.net\/main_prod_images\/KCPR1216\/1663486250.jpg",
            "emoji": "\u2728",
            "discount_percentage": 10
        },
        {
            "id": 842,
            "name": "Glitter Pencil Pouch, Waterproof Pencil Case, Stationery Organizer",
            "url": "water-glitter-pencil-pouch",
            "brand_id": "0",
            "sku": "KCPR1842",
            "price": 300,
            "mrp": 330,
            "pprice": 165,
            "category": "Stationery, Stationery: Boxes",
            "stock": 1,
            "in_stock": true,
            "image": "https:\/\/d1s4zcjwkikclq.cloudfront.net\/main_prod_images\/KCPR1842\/16967005770.jpeg",
            "emoji": "\u2728",
            "discount_percentage": 9.09
        },
        {
            "id": 172,
            "name": "Glitter Sheet",
            "url": "glitter-sheet",
            "brand_id": "0",
            "sku": "KCPR1172",
            "price": 100,
            "mrp": 120,
            "pprice": 60,
            "category": "Stationery, Stationery: Craft Items",
            "stock": 200,
            "in_stock": true,
            "image": "https:\/\/d1s4zcjwkikclq.cloudfront.net\/main_prod_images\/KCPR1172\/1663005256.jpeg",
            "emoji": "\u2728",
            "discount_percentage": 16.67
        },
        {
            "id": 899,
            "name": "Glossy Paper",
            "url": "glossy-paper",
            "brand_id": "0",
            "sku": "KCPR1899",
            "price": 20,
            "mrp": 25,
            "pprice": 12,
            "category": "Stationery, Stationery: Craft Items",
            "stock": 1,
            "in_stock": true,
            "image": "https:\/\/d1s4zcjwkikclq.cloudfront.net\/main_prod_images\/KCPR1899\/17076676950.jpg",
            "emoji": "\u2728",
            "discount_percentage": 20
        },
        {
            "id": 1508,
            "name": "Glow Rock Painting",
            "url": "glow-rock-painting",
            "brand_id": "0",
            "sku": "KCPR11508",
            "price": 539,
            "mrp": 599,
            "pprice": 230,
            "category": "Toys, Random Product",
            "stock": 1,
            "in_stock": true,
            "image": "https:\/\/d1s4zcjwkikclq.cloudfront.net\/main_prod_images\/KCPR11508\/KCPR11508_17573642344.jpeg",
            "emoji": "\u2728",
            "discount_percentage": 10.02
        },
        {
            "id": 1215,
            "name": "Glue Drops",
            "url": "glue-drops",
            "brand_id": "0",
            "sku": "KCPR11215",
            "price": 18,
            "mrp": 20,
            "pprice": 14,
            "category": "Stationery",
            "stock": 1,
            "in_stock": true,
            "image": "https:\/\/d1s4zcjwkikclq.cloudfront.net\/main_prod_images\/KCPR11215\/KCPR11215_17312263310.jpg",
            "emoji": "\u2728",
            "discount_percentage": 10
        },
        {
            "id": 897,
            "name": "Glue Gun Stick",
            "url": "glue-gun-stick",
            "brand_id": "36",
            "sku": "KCPR1897",
            "price": 10,
            "mrp": 12,
            "pprice": 6.67,
            "category": "Stationery, Stationery: Craft Items",
            "stock": 41,
            "in_stock": true,
            "image": "https:\/\/d1s4zcjwkikclq.cloudfront.net\/main_prod_images\/KCPR1897\/17076648330.jpg",
            "emoji": "\u2728",
            "discount_percentage": 16.67
        },
        {
            "id": 755,
            "name": "GoGo Fishing Game for Kids - Fun and Engaging Fishing Toy | Katyayani Creations",
            "url": "gogo-fishing-game-for-kids",
            "brand_id": "0",
            "sku": "KCPR1755",
            "price": 800,
            "mrp": 999,
            "pprice": 430,
            "category": "Toys",
            "stock": 1,
            "in_stock": true,
            "image": "https:\/\/d1s4zcjwkikclq.cloudfront.net\/main_prod_images\/KCPR1755\/1695989594.jpg",
            "emoji": "\u2728",
            "discount_percentage": 19.92
        },
        {
            "id": 706,
            "name": "Gold Stanton Stainless Steel Casserole Set \u2013 Elegant and Durable Cookware for Every Kitchen | Katyayani Creations",
            "url": "gold-stanton-stainless-steel-casserole-set-pcs",
            "brand_id": "0",
            "sku": "KCPR1706",
            "price": 2000,
            "mrp": 4500,
            "pprice": 800,
            "category": "Home & Decor, Home & Decor: Crockery, WA Diwali Items",
            "stock": 1,
            "in_stock": true,
            "image": "https:\/\/d1s4zcjwkikclq.cloudfront.net\/main_prod_images\/KCPR1706\/1689525960.jpeg",
            "emoji": "\u2728",
            "discount_percentage": 55.56
        },
        {
            "id": 801,
            "name": "Golden Kitchen",
            "url": "golden-kitchen",
            "brand_id": "0",
            "sku": "KCPR1801",
            "price": 270,
            "mrp": 300,
            "pprice": 140,
            "category": "Toys",
            "stock": 1,
            "in_stock": true,
            "image": "https:\/\/d1s4zcjwkikclq.cloudfront.net\/main_prod_images\/KCPR1801\/1696101047.jpeg",
            "emoji": "\u2728",
            "discount_percentage": 10
        },
        {
            "id": 333,
            "name": "Golden Matki Tea Light",
            "url": "golden-matki-tea-light",
            "brand_id": "0",
            "sku": "KCPR1333",
            "price": 600,
            "mrp": 650,
            "pprice": 312,
            "category": "Diwali Items",
            "stock": 11,
            "in_stock": true,
            "image": "https:\/\/d1s4zcjwkikclq.cloudfront.net\/main_prod_images\/KCPR1333\/16961849330.jpeg",
            "emoji": "\u2728",
            "discount_percentage": 7.69
        },
        {
            "id": 14,
            "name": "Golden Pot \u2013 Elegant and Decorative Golden Pot for Luxurious Home Decor | Katyayani Creations",
            "url": "golden-pot",
            "brand_id": "0",
            "sku": "KCPR1014",
            "price": 500,
            "mrp": 650,
            "pprice": 160,
            "category": "Home & Decor, Home & Decor: Vases",
            "stock": 2,
            "in_stock": true,
            "image": "https:\/\/d1s4zcjwkikclq.cloudfront.net\/main_prod_images\/KCPR1014\/OppaKRxa.jpeg",
            "emoji": "\u2728",
            "discount_percentage": 23.08
        },
        {
            "id": 263,
            "name": "Golden Windchimes \u2013 Elegant and Melodic Decorative Windchimes for Your Home | Katyayani Creations",
            "url": "golden-windchimes",
            "brand_id": "0",
            "sku": "KCPR1263",
            "price": 550,
            "mrp": 600,
            "pprice": 310,
            "category": "Home & Decor, Home & Decor: Wind Chimes, Mothers Day Store",
            "stock": 1,
            "in_stock": true,
            "image": "https:\/\/d1s4zcjwkikclq.cloudfront.net\/main_prod_images\/KCPR1263\/1666010554.jpg",
            "emoji": "\u2728",
            "discount_percentage": 8.33
        },
        {
            "id": 716,
            "name": "Googly Eyes",
            "url": "googly-eyes",
            "brand_id": "0",
            "sku": "KCPR1716",
            "price": 10,
            "mrp": 12,
            "pprice": 5,
            "category": "Stationery, Stationery: Craft Items",
            "stock": 8,
            "in_stock": true,
            "image": "https:\/\/d1s4zcjwkikclq.cloudfront.net\/main_prod_images\/KCPR1716\/1692120907.jpg",
            "emoji": "\u2728",
            "discount_percentage": 16.67
        },
        {
            "id": 851,
            "name": "Graph Copy",
            "url": "graph-copy",
            "brand_id": "7",
            "sku": "KCPR1851",
            "price": 27,
            "mrp": 30,
            "pprice": 18,
            "category": "Stationery",
            "stock": 10,
            "in_stock": true,
            "image": "https:\/\/d1s4zcjwkikclq.cloudfront.net\/main_prod_images\/KCPR1851\/16992199691.jpg",
            "emoji": "\u2728",
            "discount_percentage": 10
        },
        {
            "id": 1267,
            "name": "Graph Paper",
            "url": "graph-paper",
            "brand_id": "0",
            "sku": "KCPR11267",
            "price": 3.6,
            "mrp": 4,
            "pprice": 1,
            "category": "Stationery",
            "stock": 80,
            "in_stock": true,
            "image": "https:\/\/d1s4zcjwkikclq.cloudfront.net\/main_prod_images\/KCPR11267\/KCPR11267_17390343740.webp",
            "emoji": "\u2728",
            "discount_percentage": 10
        },
        {
            "id": 1268,
            "name": "Groove Kit",
            "url": "groove-kit",
            "brand_id": "7",
            "sku": "KCPR11268",
            "price": 10,
            "mrp": 10,
            "pprice": 7,
            "category": "Stationery",
            "stock": 56,
            "in_stock": true,
            "image": "https:\/\/d1s4zcjwkikclq.cloudfront.net\/main_prod_images\/KCPR11268\/KCPR11268_17390341980.webp",
            "emoji": "\u2728",
            "discount_percentage": 0
        },
        {
            "id": 908,
            "name": "Groove Pencils | Ergonomic Design for Comfortable Writing & Drawing",
            "url": "groove-pencils",
            "brand_id": "7",
            "sku": "KCPR1908",
            "price": 54,
            "mrp": 60,
            "pprice": 40,
            "category": "Stationery",
            "stock": 14,
            "in_stock": true,
            "image": "https:\/\/d1s4zcjwkikclq.cloudfront.net\/main_prod_images\/KCPR1908\/KCPR1908_17120658870.jpg",
            "emoji": "\u2728",
            "discount_percentage": 10
        },
        {
            "id": 388,
            "name": "Groove Retractable Eraser with Refill - Katyayani Creations",
            "url": "groove-retractable-eraser-with-refill",
            "brand_id": "7",
            "sku": "KCPR1388",
            "price": 23,
            "mrp": 25,
            "pprice": 18,
            "category": "Stationery, Stationery: Doms Kits, Stationery: Eraser & Sharpener",
            "stock": 14,
            "in_stock": true,
            "image": "https:\/\/d1s4zcjwkikclq.cloudfront.net\/main_prod_images\/KCPR1388\/1669468731.png",
            "emoji": "\u2728",
            "discount_percentage": 8
        },
        {
            "id": 1448,
            "name": "Gucgres Glass Transparent Sipper Mug with Straw and Lids",
            "url": "gucgres-glass-transparent-sipper-mug-with-straw-and-lids",
            "brand_id": "0",
            "sku": "KCPR11448",
            "price": 153,
            "mrp": 170,
            "pprice": 85,
            "category": "Toys",
            "stock": 3,
            "in_stock": true,
            "image": "https:\/\/d1s4zcjwkikclq.cloudfront.net\/main_prod_images\/KCPR11448\/KCPR11448_17545665700.webp",
            "emoji": "\u2728",
            "discount_percentage": 10
        },
        {
            "id": 1451,
            "name": "Hair Accessories Set",
            "url": "hair-accessories-set",
            "brand_id": "0",
            "sku": "KCPR11451",
            "price": 179,
            "mrp": 199,
            "pprice": 80,
            "category": "Toys",
            "stock": 158,
            "in_stock": true,
            "image": "https:\/\/d1s4zcjwkikclq.cloudfront.net\/main_prod_images\/KCPR11451\/KCPR11451_17545733050.webp",
            "emoji": "\u2728",
            "discount_percentage": 10.05
        },
        {
            "id": 1300,
            "name": "Hair Straightener Brush Electric 3-in-1 Comb with LCD Screen & Temperature Control | Affordable Styling Tool",
            "url": "hair-straightener-brush-electric-3-in-1-comb-brush-with-lcd-screen-temperature-control-display",
            "brand_id": "0",
            "sku": "KCPR11300",
            "price": 324,
            "mrp": 399,
            "pprice": 180,
            "category": "Toys",
            "stock": 2,
            "in_stock": true,
            "image": "https:\/\/d1s4zcjwkikclq.cloudfront.net\/main_prod_images\/KCPR11300\/KCPR11300_17405840510.webp",
            "emoji": "\u2728",
            "discount_percentage": 18.8
        },
        {
            "id": 791,
            "name": "Hair Stylish",
            "url": "hair-stylish",
            "brand_id": "0",
            "sku": "KCPR1791",
            "price": 350,
            "mrp": 525,
            "pprice": 130,
            "category": "Toys",
            "stock": 2,
            "in_stock": true,
            "image": "https:\/\/d1s4zcjwkikclq.cloudfront.net\/main_prod_images\/KCPR1791\/16961709350.jpeg",
            "emoji": "\u2728",
            "discount_percentage": 33.33
        },
        {
            "id": 1264,
            "name": "Half Size Pencil Color",
            "url": "natraj-half-size-pencil-color",
            "brand_id": "12",
            "sku": "KCPR11264",
            "price": 27,
            "mrp": 30,
            "pprice": 20,
            "category": "Stationery",
            "stock": 8,
            "in_stock": true,
            "image": "https:\/\/d1s4zcjwkikclq.cloudfront.net\/main_prod_images\/KCPR11264\/KCPR11264_17356427950.jpg",
            "emoji": "\u2728",
            "discount_percentage": 10
        },
        {
            "id": 1067,
            "name": "Handcrafted Clay Bucket - Natural Eco-friendly Decor | Katyayani Creations",
            "url": "clay-bucket",
            "brand_id": "37",
            "sku": "KCPR11067",
            "price": 45,
            "mrp": 50,
            "pprice": 30,
            "category": "Stationery, Toys",
            "stock": 3,
            "in_stock": true,
            "image": "https:\/\/d1s4zcjwkikclq.cloudfront.net\/main_prod_images\/KCPR11067\/KCPR11067_17142925410.jpg",
            "emoji": "\u2728",
            "discount_percentage": 10
        },
        {
            "id": 834,
            "name": "Handcrafted Scented Candle - KCPR1834 | Katyayani Creations",
            "url": "sented-candle",
            "brand_id": "0",
            "sku": "KCPR1834",
            "price": 45,
            "mrp": 60,
            "pprice": 18,
            "category": "Diwali Items, Home & Decor, WA Diwali Items",
            "stock": 19,
            "in_stock": true,
            "image": "https:\/\/d1s4zcjwkikclq.cloudfront.net\/main_prod_images\/KCPR1834\/16961821200.jpeg",
            "emoji": "\u2728",
            "discount_percentage": 25
        },
        {
            "id": 1130,
            "name": "Handcrafted Three Sisters Doll - Katyayani Creations",
            "url": "three-sisters-doll",
            "brand_id": "5",
            "sku": "KCPR11130",
            "price": 270,
            "mrp": 499,
            "pprice": 150,
            "category": "Toys",
            "stock": 1,
            "in_stock": true,
            "image": "https:\/\/d1s4zcjwkikclq.cloudfront.net\/main_prod_images\/KCPR11130\/KCPR11130_17242337910.webp",
            "emoji": "\u2728",
            "discount_percentage": 45.89
        },
        {
            "id": 1426,
            "name": "Handmade Ceramic Morning Tea Cup Set (7 Pcs) with Cattle - Elegant Home Decor & Gifting",
            "url": "morning-tea-cup-set7-pcs-with-cattle",
            "brand_id": "45",
            "sku": "KCPR11426",
            "price": 799,
            "mrp": 895,
            "pprice": 582,
            "category": "Home & Decor, Home & Decor: Crockery",
            "stock": 2,
            "in_stock": true,
            "image": "https:\/\/d1s4zcjwkikclq.cloudfront.net\/main_prod_images\/KCPR11426\/KCPR11426_17507787693.webp",
            "emoji": "\u2728",
            "discount_percentage": 10.73
        },
        {
            "id": 926,
            "name": "Handmade Doodle Art Toy \u2013 Creative and Fun Gift for Kids",
            "url": "doodle-art",
            "brand_id": "2",
            "sku": "KCPR1926",
            "price": 675,
            "mrp": 750,
            "pprice": 375,
            "category": "Toys, Random Product",
            "stock": 2,
            "in_stock": true,
            "image": "https:\/\/d1s4zcjwkikclq.cloudfront.net\/main_prod_images\/KCPR1926\/KCPR1926_17123166204.jpg",
            "emoji": "\u2728",
            "discount_percentage": 10
        },
        {
            "id": 257,
            "name": "Hanging Leg Cute Love Couple Decorative Showpiece \u2013 Charming and Romantic Home Decor | Katyayani Creations",
            "url": "hanging-leg-cute-love-couple-decorative-showpiece",
            "brand_id": "0",
            "sku": "KCPR1257",
            "price": 450,
            "mrp": 500,
            "pprice": 210,
            "category": "Home & Decor, Home & Decor:Valentine Day Special",
            "stock": 1,
            "in_stock": true,
            "image": "https:\/\/d1s4zcjwkikclq.cloudfront.net\/main_prod_images\/KCPR1257\/1664290682.jpeg",
            "emoji": "\u2728",
            "discount_percentage": 10
        },
        {
            "id": 72,
            "name": "Hanging Photo Frame Doraemon \u2013 Fun and Playful Photo Display with Doraemon Design | Katyayani Creations",
            "url": "hanging-photo-frame-doraemon",
            "brand_id": "0",
            "sku": "KCPR1072",
            "price": 400,
            "mrp": 550,
            "pprice": 210,
            "category": "Home & Decor, Home & Decor: Photo Frames",
            "stock": 1,
            "in_stock": true,
            "image": "https:\/\/d1s4zcjwkikclq.cloudfront.net\/main_prod_images\/KCPR1072\/1671306399.jpg",
            "emoji": "\u2728",
            "discount_percentage": 27.27
        },
        {
            "id": 75,
            "name": "Hanging Photo Frame Small",
            "url": "hanging-photo-frame-small",
            "brand_id": "0",
            "sku": "KCPR1075",
            "price": 250,
            "mrp": 280,
            "pprice": 115,
            "category": "Home & Decor, Home & Decor: Photo Frames",
            "stock": 1,
            "in_stock": true,
            "image": "https:\/\/d1s4zcjwkikclq.cloudfront.net\/main_prod_images\/KCPR1075\/frame1.jpeg",
            "emoji": "\u2728",
            "discount_percentage": 10.71
        },
        {
            "id": 422,
            "name": "Hanging Santa",
            "url": "hanging-santa",
            "brand_id": "0",
            "sku": "KCPR1422",
            "price": 108,
            "mrp": 120,
            "pprice": 50,
            "category": "Christmas Decoration",
            "stock": 7,
            "in_stock": true,
            "image": "https:\/\/d1s4zcjwkikclq.cloudfront.net\/main_prod_images\/KCPR1422\/1670696027.jpg",
            "emoji": "\u2728",
            "discount_percentage": 10
        },
        {
            "id": 426,
            "name": "Hanging Santa Big",
            "url": "hanging-santa-big",
            "brand_id": "0",
            "sku": "KCPR1426",
            "price": 54,
            "mrp": 60,
            "pprice": 34,
            "category": "Christmas Decoration",
            "stock": 8,
            "in_stock": true,
            "image": "https:\/\/d1s4zcjwkikclq.cloudfront.net\/main_prod_images\/KCPR1426\/1670755270.jpg",
            "emoji": "\u2728",
            "discount_percentage": 10
        },
        {
            "id": 423,
            "name": "Hanging Santa with Trumpet",
            "url": "hanging-santa-with-trumpet",
            "brand_id": "0",
            "sku": "KCPR1423",
            "price": 108,
            "mrp": 120,
            "pprice": 60,
            "category": "Christmas Decoration",
            "stock": 3,
            "in_stock": true,
            "image": "https:\/\/d1s4zcjwkikclq.cloudfront.net\/main_prod_images\/KCPR1423\/1670696233.jpg",
            "emoji": "\u2728",
            "discount_percentage": 10
        },
        {
            "id": 635,
            "name": "Happy Birthday Banner Bunting Flag",
            "url": "happy-birthday-banner-bunting-flag",
            "brand_id": "0",
            "sku": "KCPR1635",
            "price": 45,
            "mrp": 50,
            "pprice": 15,
            "category": "Birthday Accessories",
            "stock": 1,
            "in_stock": true,
            "image": "https:\/\/d1s4zcjwkikclq.cloudfront.net\/main_prod_images\/KCPR1635\/1681502939.jpg",
            "emoji": "\u2728",
            "discount_percentage": 10
        },
        {
            "id": 98,
            "name": "Happy Birthday Set Box",
            "url": "happy-birthday-set-box",
            "brand_id": "0",
            "sku": "KCPR1098",
            "price": 225,
            "mrp": 250,
            "pprice": 60,
            "category": "Birthday Accessories",
            "stock": 4,
            "in_stock": true,
            "image": "https:\/\/d1s4zcjwkikclq.cloudfront.net\/main_prod_images\/KCPR1098\/1664814060.jpeg",
            "emoji": "\u2728",
            "discount_percentage": 10
        },
        {
            "id": 928,
            "name": "Happy Toy Chick",
            "url": "happy-toy-chick",
            "brand_id": "0",
            "sku": "KCPR1928",
            "price": 54,
            "mrp": 60,
            "pprice": 28,
            "category": "Toys",
            "stock": 5,
            "in_stock": true,
            "image": "https:\/\/d1s4zcjwkikclq.cloudfront.net\/main_prod_images\/KCPR1928\/KCPR1928_17125960910.jpg",
            "emoji": "\u2728",
            "discount_percentage": 10
        },
        {
            "id": 1544,
            "name": "Hard Shell School Bags",
            "url": "hard-shell-school-bags",
            "brand_id": "0",
            "sku": "KCPR11544",
            "price": 297,
            "mrp": 330,
            "pprice": 165,
            "category": "Return Gift Items",
            "stock": 3,
            "in_stock": true,
            "image": "https:\/\/d1s4zcjwkikclq.cloudfront.net\/main_prod_images\/KCPR11544\/KCPR11544_17577635970.jpg",
            "emoji": "\u2728",
            "discount_percentage": 10
        },
        {
            "id": 91,
            "name": "Heart-Shaped Gift Box with Teddy & Artificial Roses \u2013 Perfect Romantic Gift",
            "url": "heart-shape-gift-box-with-teddy-and-artificial-rose",
            "brand_id": "0",
            "sku": "KCPR1091",
            "price": 175,
            "mrp": 200,
            "pprice": 55,
            "category": "Home & Decor, Home & Decor:Valentine Day Special, Return Gift Items, Teacher Day special",
            "stock": 4,
            "in_stock": true,
            "image": "https:\/\/d1s4zcjwkikclq.cloudfront.net\/main_prod_images\/KCPR1091\/1661362786.jpg",
            "emoji": "\u2728",
            "discount_percentage": 12.5
        },
        {
            "id": 1240,
            "name": "Hello Master | Glass Water Bottle 350 ML for Kids",
            "url": "hello-master-glass-water-bottle-350-ml-for-kids",
            "brand_id": "0",
            "sku": "KCPR11240",
            "price": 69,
            "mrp": 99,
            "pprice": 46,
            "category": "Return Gift Items, Toys",
            "stock": 2,
            "in_stock": true,
            "image": "https:\/\/d1s4zcjwkikclq.cloudfront.net\/main_prod_images\/KCPR11240\/KCPR11240_17342896793.webp",
            "emoji": "\u2728",
            "discount_percentage": 30.3
        },
        {
            "id": 1392,
            "name": "Herry Zeep",
            "url": "herry-zeep",
            "brand_id": "0",
            "sku": "KCPR11392",
            "price": 449,
            "mrp": 499,
            "pprice": 150,
            "category": "Toys",
            "stock": 1,
            "in_stock": true,
            "image": "https:\/\/d1s4zcjwkikclq.cloudfront.net\/main_prod_images\/KCPR11392\/KCPR11392_17446591760.jpeg",
            "emoji": "\u2728",
            "discount_percentage": 10.02
        },
        {
            "id": 896,
            "name": "High-Performance Glue Gun | Versatile & Reliable Adhesive Tool",
            "url": "glue-gun",
            "brand_id": "0",
            "sku": "KCPR1896",
            "price": 249,
            "mrp": 299,
            "pprice": 100,
            "category": "Stationery",
            "stock": 1,
            "in_stock": true,
            "image": "https:\/\/d1s4zcjwkikclq.cloudfront.net\/main_prod_images\/KCPR1896\/17076652740.jpg",
            "emoji": "\u2728",
            "discount_percentage": 16.72
        },
        {
            "id": 1116,
            "name": "High-Quality Oil Tanker | Katyayani Creations",
            "url": "oil-tanker",
            "brand_id": "41",
            "sku": "KCPR11116",
            "price": 378,
            "mrp": 504,
            "pprice": 210,
            "category": "Toys",
            "stock": 1,
            "in_stock": true,
            "image": "https:\/\/d1s4zcjwkikclq.cloudfront.net\/main_prod_images\/KCPR11116\/KCPR11116_17237258661.jpg",
            "emoji": "\u2728",
            "discount_percentage": 25
        },
        {
            "id": 1064,
            "name": "Highlighter",
            "url": "highlighter",
            "brand_id": "11",
            "sku": "KCPR11064",
            "price": 22.5,
            "mrp": 25,
            "pprice": 14,
            "category": "Stationery",
            "stock": 10,
            "in_stock": true,
            "image": "https:\/\/d1s4zcjwkikclq.cloudfront.net\/main_prod_images\/KCPR11064\/KCPR11064_17142994470.jpg",
            "emoji": "\u2728",
            "discount_percentage": 10
        },
        {
            "id": 1256,
            "name": "Hot Wheels Car Motor Show 5 Pack 2023 Multi- Color 2016 Ford GT Race, Crescendo, 1967 Ford GT40 MK, IV Lamborghini Countach PACE CAR, Aston Martin ONE",
            "url": "hot-wheels-car-motor-show-5-pack-2023-multi-color-2016-ford-gt-race-crescendo-1967-ford-gt40-mk-iv-lamborghini-countach-pace-car-aston-martin-one",
            "brand_id": "0",
            "sku": "KCPR11256",
            "price": 360,
            "mrp": 400,
            "pprice": 180,
            "category": "Toys",
            "stock": 1,
            "in_stock": true,
            "image": "https:\/\/d1s4zcjwkikclq.cloudfront.net\/main_prod_images\/KCPR11256\/KCPR11256_17357437963.jpg",
            "emoji": "\u2728",
            "discount_percentage": 10
        },
        {
            "id": 1257,
            "name": "Hot Wheels Metals car toys set of 3 different car metal",
            "url": "hot-wheel-cars-3-pcs",
            "brand_id": "0",
            "sku": "KCPR11257",
            "price": 270,
            "mrp": 299,
            "pprice": 130,
            "category": "Toys",
            "stock": 1,
            "in_stock": true,
            "image": "https:\/\/d1s4zcjwkikclq.cloudfront.net\/main_prod_images\/KCPR11257\/KCPR11257_17357427912.webp",
            "emoji": "\u2728",
            "discount_percentage": 9.7
        },
        {
            "id": 1220,
            "name": "House Shaped Piggy Bank with Stickers, Handle and Keys for Kids",
            "url": "house-shaped-piggy-bank-with-stickers-handle-and-keys-for-kids",
            "brand_id": "0",
            "sku": "KCPR11220",
            "price": 232,
            "mrp": 310,
            "pprice": 155,
            "category": "Toys",
            "stock": 1,
            "in_stock": true,
            "image": "https:\/\/d1s4zcjwkikclq.cloudfront.net\/main_prod_images\/KCPR11220\/KCPR11220_17342828902.webp",
            "emoji": "\u2728",
            "discount_percentage": 25.16
        },
        {
            "id": 1112,
            "name": "Hungry Frog",
            "url": "hungry-frog",
            "brand_id": "0",
            "sku": "KCPR11112",
            "price": 324,
            "mrp": 699,
            "pprice": 180,
            "category": "Toys",
            "stock": 1,
            "in_stock": true,
            "image": "https:\/\/d1s4zcjwkikclq.cloudfront.net\/main_prod_images\/KCPR11112\/KCPR11112_17237758840.jpg",
            "emoji": "\u2728",
            "discount_percentage": 53.65
        },
        {
            "id": 1512,
            "name": "I Love You Doll",
            "url": "i-love-you-doll",
            "brand_id": "0",
            "sku": "KCPR11512",
            "price": 300,
            "mrp": 499,
            "pprice": 70,
            "category": "Toys",
            "stock": 1,
            "in_stock": true,
            "image": "",
            "emoji": "\u2728",
            "discount_percentage": 39.88
        },
        {
            "id": 535,
            "name": "IRIS lavender Diffuser Set",
            "url": "iris-lavender-diffuser-set",
            "brand_id": "0",
            "sku": "KCPR1535",
            "price": 250,
            "mrp": 350,
            "pprice": 100,
            "category": "Home & Decor",
            "stock": 9,
            "in_stock": true,
            "image": "https:\/\/d1s4zcjwkikclq.cloudfront.net\/main_prod_images\/KCPR1535\/1673348124.jpeg",
            "emoji": "\u2728",
            "discount_percentage": 28.57
        },
        {
            "id": 714,
            "name": "Ice Cream Sticks",
            "url": "ice-cream-sticks",
            "brand_id": "0",
            "sku": "KCPR1714",
            "price": 27,
            "mrp": 30,
            "pprice": 15,
            "category": "Stationery, Stationery: Craft Items",
            "stock": 90,
            "in_stock": true,
            "image": "https:\/\/d1s4zcjwkikclq.cloudfront.net\/main_prod_images\/KCPR1714\/1692120543.jpg",
            "emoji": "\u2728",
            "discount_percentage": 10
        },
        {
            "id": 71,
            "name": "Ice Mugs Design Mix",
            "url": "ice-mugs-design-mix",
            "brand_id": "0",
            "sku": "KCPR1071",
            "price": 270,
            "mrp": 350,
            "pprice": 165,
            "category": "Return Gift Items, Toys",
            "stock": 1,
            "in_stock": true,
            "image": "https:\/\/d1s4zcjwkikclq.cloudfront.net\/main_prod_images\/KCPR1071\/icemug3.jpeg",
            "emoji": "\u2728",
            "discount_percentage": 22.86
        },
        {
            "id": 861,
            "name": "India Map Political\/Physical",
            "url": "india-political-map",
            "brand_id": "0",
            "sku": "KCPR1861",
            "price": 2,
            "mrp": 4,
            "pprice": 0.5,
            "category": "Stationery",
            "stock": 63,
            "in_stock": true,
            "image": "https:\/\/d1s4zcjwkikclq.cloudfront.net\/main_prod_images\/KCPR1861\/17021389680.webp",
            "emoji": "\u2728",
            "discount_percentage": 50
        },
        {
            "id": 1498,
            "name": "India\/world Map",
            "url": "indiaworld-map",
            "brand_id": "0",
            "sku": "KCPR11498",
            "price": 357,
            "mrp": 397,
            "pprice": 135,
            "category": "Toys",
            "stock": 2,
            "in_stock": true,
            "image": "https:\/\/d1s4zcjwkikclq.cloudfront.net\/main_prod_images\/KCPR11498\/KCPR11498_17573355950.jpg",
            "emoji": "\u2728",
            "discount_percentage": 10.08
        },
        {
            "id": 932,
            "name": "Infant Rattle Set",
            "url": "dolly-infant-rattle-set",
            "brand_id": "30",
            "sku": "KCPR1932",
            "price": 317,
            "mrp": 397,
            "pprice": 135,
            "category": "Toys",
            "stock": 3,
            "in_stock": true,
            "image": "https:\/\/d1s4zcjwkikclq.cloudfront.net\/main_prod_images\/KCPR1932\/KCPR1932_17126573720.jpg",
            "emoji": "\u2728",
            "discount_percentage": 20.15
        },
        {
            "id": 1173,
            "name": "Infant Rattle Set",
            "url": "infant-rattle-set",
            "brand_id": "30",
            "sku": "KCPR11173",
            "price": 368,
            "mrp": 460,
            "pprice": 155,
            "category": "Toys",
            "stock": 3,
            "in_stock": true,
            "image": "https:\/\/d1s4zcjwkikclq.cloudfront.net\/main_prod_images\/KCPR11173\/KCPR11173_17242347135.jpg",
            "emoji": "\u2728",
            "discount_percentage": 20
        },
        {
            "id": 140,
            "name": "International Business",
            "url": "international-business",
            "brand_id": "1",
            "sku": "KCPR1140",
            "price": 329,
            "mrp": 410,
            "pprice": 165,
            "category": "Toys: Board Games",
            "stock": 1,
            "in_stock": true,
            "image": "https:\/\/d1s4zcjwkikclq.cloudfront.net\/main_prod_images\/KCPR1140\/1662920144.webp",
            "emoji": "\u2728",
            "discount_percentage": 19.76
        },
        {
            "id": 220,
            "name": "Invisible Ink Magic Pen \u2013 Write Secret Messages with Fun!",
            "url": "invisible-ink-magic-pen",
            "brand_id": "0",
            "sku": "KCPR1220",
            "price": 80,
            "mrp": 100,
            "pprice": 45.25,
            "category": "Kanjak Gifts, Stationery, Stationery: Pens",
            "stock": 19,
            "in_stock": true,
            "image": "https:\/\/d1s4zcjwkikclq.cloudfront.net\/main_prod_images\/KCPR1220\/1663490548.jpeg",
            "emoji": "\u2728",
            "discount_percentage": 20
        },
        {
            "id": 108,
            "name": "Its a Girl Balloon",
            "url": "its-a-girl-balloon",
            "brand_id": "0",
            "sku": "KCPR1108",
            "price": 120,
            "mrp": 150,
            "pprice": 60,
            "category": "Birthday Accessories",
            "stock": 2,
            "in_stock": true,
            "image": "https:\/\/d1s4zcjwkikclq.cloudfront.net\/main_prod_images\/KCPR1108\/balloon.jpeg",
            "emoji": "\u2728",
            "discount_percentage": 20
        },
        {
            "id": 1330,
            "name": "JK Excel 90 GSM A4 Size Bond Paper - High-Quality Printing Paper",
            "url": "jk-excel-90-gsm-a4-size-bond-paper",
            "brand_id": "0",
            "sku": "KCPR11330",
            "price": 2,
            "mrp": 2,
            "pprice": 0.8,
            "category": "Stationery",
            "stock": 100,
            "in_stock": true,
            "image": "https:\/\/d1s4zcjwkikclq.cloudfront.net\/main_prod_images\/KCPR11330\/KCPR11330_17428397080.jpeg",
            "emoji": "\u2728",
            "discount_percentage": 0
        },
        {
            "id": 148,
            "name": "Jenga Blocks Timber Tower Tumbling Game",
            "url": "jenga-blocks-timber-tower-tumbling-game",
            "brand_id": "0",
            "sku": "KCPR1148",
            "price": 420,
            "mrp": 599,
            "pprice": 200,
            "category": "Toys",
            "stock": 1,
            "in_stock": true,
            "image": "https:\/\/d1s4zcjwkikclq.cloudfront.net\/main_prod_images\/KCPR1148\/1662921069.jpg",
            "emoji": "\u2728",
            "discount_percentage": 29.88
        },
        {
            "id": 512,
            "name": "Jewellery Boutique Fun Game",
            "url": "jewellery-boutique-fun-game",
            "brand_id": "1",
            "sku": "KCPR1512",
            "price": 260,
            "mrp": 325,
            "pprice": 125,
            "category": "Toys, Toys: Board Games",
            "stock": 1,
            "in_stock": true,
            "image": "https:\/\/d1s4zcjwkikclq.cloudfront.net\/main_prod_images\/KCPR1512\/1673256742.jpg",
            "emoji": "\u2728",
            "discount_percentage": 20
        },
        {
            "id": 1280,
            "name": "Jewellery Organiser for Easy Storage & Organizing - Stylish, Compact, and Affordable | Katyayani Creations",
            "url": "jewellery-organiser",
            "brand_id": "0",
            "sku": "KCPR11280",
            "price": 180,
            "mrp": 200,
            "pprice": 105,
            "category": "Toys",
            "stock": 1,
            "in_stock": true,
            "image": "https:\/\/d1s4zcjwkikclq.cloudfront.net\/main_prod_images\/KCPR11280\/KCPR11280_17405856340.webp",
            "emoji": "\u2728",
            "discount_percentage": 10
        },
        {
            "id": 1171,
            "name": "Jhoomer",
            "url": "jhoomer",
            "brand_id": "0",
            "sku": "KCPR11171",
            "price": 180,
            "mrp": 240,
            "pprice": 100,
            "category": "Toys",
            "stock": 1,
            "in_stock": true,
            "image": "https:\/\/d1s4zcjwkikclq.cloudfront.net\/main_prod_images\/KCPR11171\/KCPR11171_17238894170.jpg",
            "emoji": "\u2728",
            "discount_percentage": 25
        },
        {
            "id": 240,
            "name": "Jiffy Gel Pens (Set of 5)",
            "url": "jiffy-gel-pens-set-of-5",
            "brand_id": "31",
            "sku": "KCPR1240",
            "price": 32,
            "mrp": 35,
            "pprice": 22.5,
            "category": "Stationery: Pens, Stationery",
            "stock": 23,
            "in_stock": true,
            "image": "https:\/\/d1s4zcjwkikclq.cloudfront.net\/main_prod_images\/KCPR1240\/1664041916.jpg",
            "emoji": "\u2728",
            "discount_percentage": 8.57
        },
        {
            "id": 144,
            "name": "Jumping Monkey Jr.",
            "url": "jumping-monkey-jr",
            "brand_id": "0",
            "sku": "KCPR1144",
            "price": 329,
            "mrp": 410,
            "pprice": 165,
            "category": "Toys: Board Games",
            "stock": 1,
            "in_stock": true,
            "image": "https:\/\/d1s4zcjwkikclq.cloudfront.net\/main_prod_images\/KCPR1144\/1662920434.webp",
            "emoji": "\u2728",
            "discount_percentage": 19.76
        },
        {
            "id": 1243,
            "name": "Jungle theme pen Stand",
            "url": "jungle-theme-pen-stand",
            "brand_id": "0",
            "sku": "KCPR11243",
            "price": 50,
            "mrp": 70,
            "pprice": 33,
            "category": "Return Gift Items, Stationery, Toys",
            "stock": 6,
            "in_stock": true,
            "image": "https:\/\/d1s4zcjwkikclq.cloudfront.net\/main_prod_images\/KCPR11243\/KCPR11243_17342907773.webp",
            "emoji": "\u2728",
            "discount_percentage": 28.57
        },
        {
            "id": 372,
            "name": "Junior Art Kit Bag for Kids - Creative Stationery Set",
            "url": "junior-art-kit-bag",
            "brand_id": "7",
            "sku": "KCPR1372",
            "price": 342,
            "mrp": 380,
            "pprice": 304,
            "category": "Stationery, Stationery: Colors, Stationery: Doms Kits",
            "stock": 1,
            "in_stock": true,
            "image": "https:\/\/d1s4zcjwkikclq.cloudfront.net\/main_prod_images\/KCPR1372\/1668323354.jpg",
            "emoji": "\u2728",
            "discount_percentage": 10
        },
        {
            "id": 1527,
            "name": "Jute Rangoli Plate NT2100",
            "url": "jute-rangoli-plate-nt2100",
            "brand_id": "0",
            "sku": "KCPR11527",
            "price": 1890,
            "mrp": 2100,
            "pprice": 820,
            "category": "Home & Decor, Diwali Items",
            "stock": 1,
            "in_stock": true,
            "image": "https:\/\/d1s4zcjwkikclq.cloudfront.net\/main_prod_images\/KCPR11527\/KCPR11527_17585486390.jpeg",
            "emoji": "\u2728",
            "discount_percentage": 10
        },
        {
            "id": 1115,
            "name": "KUV",
            "url": "kuv",
            "brand_id": "41",
            "sku": "KCPR11115",
            "price": 297,
            "mrp": 430,
            "pprice": 165,
            "category": "Toys",
            "stock": 2,
            "in_stock": true,
            "image": "https:\/\/d1s4zcjwkikclq.cloudfront.net\/main_prod_images\/KCPR11115\/KCPR11115_17238853012.jpg",
            "emoji": "\u2728",
            "discount_percentage": 30.93
        },
        {
            "id": 1548,
            "name": "Kanjak Multi-Color Cartoon Print Purse",
            "url": "kanjak-multicolor-cartoon-print-purse",
            "brand_id": "0",
            "sku": "KCPR11548",
            "price": 36,
            "mrp": 40,
            "pprice": 20,
            "category": "Home & Decor",
            "stock": 12,
            "in_stock": true,
            "image": "https:\/\/d1s4zcjwkikclq.cloudfront.net\/main_prod_images\/KCPR11548\/KCPR11548_17577653680.jpg",
            "emoji": "\u2728",
            "discount_percentage": 10
        },
        {
            "id": 1547,
            "name": "Kanjak Rajasthani Pooja Purse",
            "url": "kanjak-rajasthani-pooja-purse",
            "brand_id": "0",
            "sku": "KCPR11547",
            "price": 45,
            "mrp": 50,
            "pprice": 15,
            "category": "Return Gift Items",
            "stock": 24,
            "in_stock": true,
            "image": "https:\/\/d1s4zcjwkikclq.cloudfront.net\/main_prod_images\/KCPR11547\/KCPR11547_17577647920.jpg",
            "emoji": "\u2728",
            "discount_percentage": 10
        },
        {
            "id": 454,
            "name": "Katyayani Creations Colouring Mat for Kids, Educational Toy",
            "url": "colouring-mat",
            "brand_id": "2",
            "sku": "KCPR1454",
            "price": 448,
            "mrp": 560,
            "pprice": 200,
            "category": "Toys",
            "stock": 2,
            "in_stock": true,
            "image": "https:\/\/d1s4zcjwkikclq.cloudfront.net\/main_prod_images\/KCPR1454\/1673284964.jpg",
            "emoji": "\u2728",
            "discount_percentage": 20
        },
        {
            "id": 757,
            "name": "Katyayani Creations Dessert Mart Toy for Kids Fun Play",
            "url": "dessert-mart",
            "brand_id": "18",
            "sku": "KCPR1757",
            "price": 584,
            "mrp": 649,
            "pprice": 250,
            "category": "Toys",
            "stock": 1,
            "in_stock": true,
            "image": "https:\/\/d1s4zcjwkikclq.cloudfront.net\/main_prod_images\/KCPR1757\/1695990432.jpg",
            "emoji": "\u2728",
            "discount_percentage": 10.02
        },
        {
            "id": 652,
            "name": "Katyayani Creations Hammer Ball Toy for Kids",
            "url": "hammer-ball",
            "brand_id": "5",
            "sku": "KCPR1652",
            "price": 692,
            "mrp": 769,
            "pprice": 200,
            "category": "Toys, Toys: Creativity Kits",
            "stock": 1,
            "in_stock": true,
            "image": "https:\/\/d1s4zcjwkikclq.cloudfront.net\/main_prod_images\/KCPR1652\/1681547249.webp",
            "emoji": "\u2728",
            "discount_percentage": 10.01
        },
        {
            "id": 1218,
            "name": "Katyayani Creations Premium Stationery Kit for Office, School and College Students",
            "url": "stationary-kit",
            "brand_id": "0",
            "sku": "KCPR11218",
            "price": 99,
            "mrp": 149,
            "pprice": 60,
            "category": "Stationery",
            "stock": 10,
            "in_stock": true,
            "image": "https:\/\/d1s4zcjwkikclq.cloudfront.net\/main_prod_images\/KCPR11218\/KCPR11218_17338414140.jpeg",
            "emoji": "\u2728",
            "discount_percentage": 33.56
        },
        {
            "id": 1420,
            "name": "Katyayani Creations Tyre Eraser for Precise Erasing, High Quality Stationery",
            "url": "tyre-eraser",
            "brand_id": "7",
            "sku": "KCPR11420",
            "price": 10,
            "mrp": 10,
            "pprice": 7,
            "category": "Stationery, Stationery: Doms Kits, Stationery: Eraser & Sharpener",
            "stock": 15,
            "in_stock": true,
            "image": "https:\/\/d1s4zcjwkikclq.cloudfront.net\/main_prod_images\/KCPR11420\/KCPR11420_17492197470.jpeg",
            "emoji": "\u2728",
            "discount_percentage": 0
        },
        {
            "id": 1424,
            "name": "Katyayani Poster Colors (Shade of 12) - Vibrant & Smooth Water-Based Paints for Artists & Students | KC-PR11424",
            "url": "poster-color-shade-of-12",
            "brand_id": "7",
            "sku": "KCPR11424",
            "price": 171,
            "mrp": 190,
            "pprice": 125,
            "category": "Stationery, Stationery: Colors",
            "stock": 12,
            "in_stock": true,
            "image": "https:\/\/d1s4zcjwkikclq.cloudfront.net\/main_prod_images\/KCPR11424\/KCPR11424_17505283142.jpeg",
            "emoji": "\u2728",
            "discount_percentage": 10
        },
        {
            "id": 1229,
            "name": "Kawaii Learning Drawing Board Sketch Pad Doodle Writing Art Child Girl Gift",
            "url": "kawaii-learning-drawing-board-sketch-pad-doodle-writing-art-child-girl-gift",
            "brand_id": "0",
            "sku": "KCPR11229",
            "price": 60,
            "mrp": 99,
            "pprice": 40,
            "category": "Stationery, Toys",
            "stock": 9,
            "in_stock": true,
            "image": "https:\/\/d1s4zcjwkikclq.cloudfront.net\/main_prod_images\/KCPR11229\/KCPR11229_17342899220.webp",
            "emoji": "\u2728",
            "discount_percentage": 39.39
        },
        {
            "id": 1109,
            "name": "Key Chains",
            "url": "key-chains",
            "brand_id": "0",
            "sku": "KCPR11109",
            "price": 89,
            "mrp": 99,
            "pprice": 59.25,
            "category": "Return Gift Items",
            "stock": 5,
            "in_stock": true,
            "image": "",
            "emoji": "\u2728",
            "discount_percentage": 10.1
        },
        {
            "id": 933,
            "name": "Kiddie Laundry Play Set for Kids, Toy Washing Machine and Iron",
            "url": "angaa-laundry-set",
            "brand_id": "0",
            "sku": "KCPR1933",
            "price": 775,
            "mrp": 860,
            "pprice": 220,
            "category": "Toys",
            "stock": 1,
            "in_stock": true,
            "image": "https:\/\/d1s4zcjwkikclq.cloudfront.net\/main_prod_images\/KCPR1933\/KCPR1933_17124761850.jpg",
            "emoji": "\u2728",
            "discount_percentage": 9.88
        },
        {
            "id": 1141,
            "name": "Kids Football",
            "url": "kids-football",
            "brand_id": "0",
            "sku": "KCPR11141",
            "price": 90,
            "mrp": 199,
            "pprice": 50,
            "category": "Toys",
            "stock": 7,
            "in_stock": true,
            "image": "https:\/\/d1s4zcjwkikclq.cloudfront.net\/main_prod_images\/KCPR11141\/KCPR11141_17265832400.jpeg",
            "emoji": "\u2728",
            "discount_percentage": 54.77
        },
        {
            "id": 1408,
            "name": "Kids Hardshell Backpack - Durable & Stylish School Bag for Children",
            "url": "hardshell-back-pack-for-kids",
            "brand_id": "0",
            "sku": "KCPR11408",
            "price": 449,
            "mrp": 499,
            "pprice": 185,
            "category": "Toys",
            "stock": 1,
            "in_stock": true,
            "image": "https:\/\/d1s4zcjwkikclq.cloudfront.net\/main_prod_images\/KCPR11408\/KCPR11408_17458314950.webp",
            "emoji": "\u2728",
            "discount_percentage": 10.02
        },
        {
            "id": 690,
            "name": "Kids Nail Art",
            "url": "kids-nail-art",
            "brand_id": "0",
            "sku": "KCPR1690",
            "price": 120,
            "mrp": 150,
            "pprice": 60,
            "category": "Return Gift Items, Toys",
            "stock": 2,
            "in_stock": true,
            "image": "https:\/\/d1s4zcjwkikclq.cloudfront.net\/main_prod_images\/KCPR1690\/1681563708.jpg",
            "emoji": "\u2728",
            "discount_percentage": 20
        },
        {
            "id": 1351,
            "name": "Kids Nail Art Tattoo Kit for Girls, DIY Nail Art Supplies",
            "url": "tatto-kit-nail-art",
            "brand_id": "0",
            "sku": "KCPR11351",
            "price": 495,
            "mrp": 549,
            "pprice": 210,
            "category": "Toys",
            "stock": 1,
            "in_stock": true,
            "image": "https:\/\/d1s4zcjwkikclq.cloudfront.net\/main_prod_images\/KCPR11351\/KCPR11351_17447308281.jpg",
            "emoji": "\u2728",
            "discount_percentage": 9.84
        },
        {
            "id": 385,
            "name": "Kids Pop It Game Spiral Diary",
            "url": "kids-pop-it-game-spiral-diary",
            "brand_id": "0",
            "sku": "KCPR1385",
            "price": 315,
            "mrp": 350,
            "pprice": 160,
            "category": "Return Gift Items",
            "stock": 1,
            "in_stock": true,
            "image": "https:\/\/d1s4zcjwkikclq.cloudfront.net\/main_prod_images\/KCPR1385\/1669467930.jpg",
            "emoji": "\u2728",
            "discount_percentage": 10
        },
        {
            "id": 1024,
            "name": "Kids Racket",
            "url": "kids-racket",
            "brand_id": "0",
            "sku": "KCPR11024",
            "price": 240,
            "mrp": 340,
            "pprice": 120,
            "category": "Toys",
            "stock": 1,
            "in_stock": true,
            "image": "https:\/\/d1s4zcjwkikclq.cloudfront.net\/main_prod_images\/KCPR11024\/KCPR11024_17126581740.jpeg",
            "emoji": "\u2728",
            "discount_percentage": 29.41
        },
        {
            "id": 185,
            "name": "Kids Style Table LED Lamp with Clock - Fun and Functional Lighting for Children | Katyayani Creations",
            "url": "kids-style-table-led-lamp-with-clock",
            "brand_id": "0",
            "sku": "KCPR1185",
            "price": 600,
            "mrp": 660,
            "pprice": 325,
            "category": "Home & Decor, Home & Decor: Clocks, Home & Decor: Lamps, WA Diwali Items",
            "stock": 1,
            "in_stock": true,
            "image": "https:\/\/d1s4zcjwkikclq.cloudfront.net\/main_prod_images\/KCPR1185\/1663092534.jpeg",
            "emoji": "\u2728",
            "discount_percentage": 9.09
        },
        {
            "id": 1542,
            "name": "Kids Transparent unisex backpack",
            "url": "kids-transparent-unisex-backpack",
            "brand_id": "0",
            "sku": "KCPR11542",
            "price": 522,
            "mrp": 580,
            "pprice": 290,
            "category": "Return Gift Items",
            "stock": 2,
            "in_stock": true,
            "image": "https:\/\/d1s4zcjwkikclq.cloudfront.net\/main_prod_images\/KCPR11542\/KCPR11542_17577108570.jpg",
            "emoji": "\u2728",
            "discount_percentage": 10
        },
        {
            "id": 922,
            "name": "Kids Walkie Talkie - Fun and Durable Communication for Kids",
            "url": "kids-walkie-talkie",
            "brand_id": "0",
            "sku": "KCPR1922",
            "price": 720,
            "mrp": 800,
            "pprice": 190,
            "category": "Toys",
            "stock": 1,
            "in_stock": true,
            "image": "https:\/\/d1s4zcjwkikclq.cloudfront.net\/main_prod_images\/KCPR1922\/KCPR1922_17123049970.jpg",
            "emoji": "\u2728",
            "discount_percentage": 10
        },
        {
            "id": 1134,
            "name": "Kids Xylophone Musical Instrument, Childrens Xylophone Toy",
            "url": "xylophone",
            "brand_id": "5",
            "sku": "KCPR11134",
            "price": 468,
            "mrp": 969,
            "pprice": 260,
            "category": "Toys",
            "stock": 1,
            "in_stock": true,
            "image": "https:\/\/d1s4zcjwkikclq.cloudfront.net\/main_prod_images\/KCPR11134\/KCPR11134_17238842950.jpg",
            "emoji": "\u2728",
            "discount_percentage": 51.7
        },
        {
            "id": 1517,
            "name": "Kirat String Hockey",
            "url": "kirat-string-hockey",
            "brand_id": "0",
            "sku": "KCPR11517",
            "price": 1034,
            "mrp": 1149,
            "pprice": 460,
            "category": "Toys",
            "stock": 1,
            "in_stock": true,
            "image": "",
            "emoji": "\u2728",
            "discount_percentage": 10.01
        },
        {
            "id": 1174,
            "name": "Kitchen Playset 26 Pieces \u2013 Fun and Interactive Pretend Play for Kids | Katyayani Creations",
            "url": "kitchen-playset-26-pieces",
            "brand_id": "18",
            "sku": "KCPR11174",
            "price": 1008,
            "mrp": 1499,
            "pprice": 560,
            "category": "Toys",
            "stock": 1,
            "in_stock": true,
            "image": "https:\/\/d1s4zcjwkikclq.cloudfront.net\/main_prod_images\/KCPR11174\/KCPR11174_17238183383.jpg",
            "emoji": "\u2728",
            "discount_percentage": 32.76
        },
        {
            "id": 1009,
            "name": "Kitchen Sink \u2013 Realistic and Functional Play Sink for Kids | Katyayani Creations",
            "url": "kitchen-sink",
            "brand_id": "0",
            "sku": "KCPR11009",
            "price": 960,
            "mrp": 1200,
            "pprice": 480,
            "category": "Toys",
            "stock": 1,
            "in_stock": true,
            "image": "https:\/\/d1s4zcjwkikclq.cloudfront.net\/main_prod_images\/KCPR11009\/KCPR11009_17124786480.webp",
            "emoji": "\u2728",
            "discount_percentage": 20
        },
        {
            "id": 502,
            "name": "Kitchen Ware Fruits Toy for Kids",
            "url": "kitchen-ware-fruits-toy-for-kids",
            "brand_id": "0",
            "sku": "KCPR1502",
            "price": 135,
            "mrp": 150,
            "pprice": 55,
            "category": "Toys",
            "stock": 1,
            "in_stock": true,
            "image": "https:\/\/d1s4zcjwkikclq.cloudfront.net\/main_prod_images\/KCPR1502\/1673252437.jpg",
            "emoji": "\u2728",
            "discount_percentage": 10
        },
        {
            "id": 718,
            "name": "Kulfi Stick",
            "url": "kulfi-stick",
            "brand_id": "0",
            "sku": "KCPR1718",
            "price": 54,
            "mrp": 60,
            "pprice": 30,
            "category": "Stationery, Stationery: Craft Items",
            "stock": 1,
            "in_stock": true,
            "image": "https:\/\/d1s4zcjwkikclq.cloudfront.net\/main_prod_images\/KCPR1718\/1692120575.jpg",
            "emoji": "\u2728",
            "discount_percentage": 10
        },
        {
            "id": 1543,
            "name": "Kuromi Hard Shell Bag",
            "url": "kuromi-hard-shell-bag",
            "brand_id": "0",
            "sku": "KCPR11543",
            "price": 351,
            "mrp": 390,
            "pprice": 195,
            "category": "Return Gift Items",
            "stock": 1,
            "in_stock": true,
            "image": "https:\/\/d1s4zcjwkikclq.cloudfront.net\/main_prod_images\/KCPR11543\/KCPR11543_17577774920.jpg",
            "emoji": "\u2728",
            "discount_percentage": 10
        },
        {
            "id": 1440,
            "name": "L Folder",
            "url": "l-folder",
            "brand_id": "0",
            "sku": "KCPR11440",
            "price": 9,
            "mrp": 10,
            "pprice": 4,
            "category": "Stationery",
            "stock": 12,
            "in_stock": true,
            "image": "",
            "emoji": "\u2728",
            "discount_percentage": 10
        },
        {
            "id": 1222,
            "name": "LCD Writing Pencil Case Writing Tablet Pencil Box",
            "url": "lcd-writing-pencil-case-writing-tablet-pencil-box",
            "brand_id": "0",
            "sku": "KCPR11222",
            "price": 300,
            "mrp": 350,
            "pprice": 135,
            "category": "Stationery, Stationery: Boxes, Toys",
            "stock": 4,
            "in_stock": true,
            "image": "https:\/\/d1s4zcjwkikclq.cloudfront.net\/main_prod_images\/KCPR11222\/KCPR11222_17342904275.webp",
            "emoji": "\u2728",
            "discount_percentage": 14.29
        },
        {
            "id": 1302,
            "name": "LCD Writing Tablet Pad for Kids - Digital Magic Slate, Scribble Doodle Drawing Rough Pad",
            "url": "lcd-writing-tablet-pad-for-kids-digital-magic-slate-scribble-doodle-drawing-rough-pad",
            "brand_id": "0",
            "sku": "KCPR11302",
            "price": 180,
            "mrp": 200,
            "pprice": 95,
            "category": "Toys",
            "stock": 1,
            "in_stock": true,
            "image": "https:\/\/d1s4zcjwkikclq.cloudfront.net\/main_prod_images\/KCPR11302\/KCPR11302_17405871690.webp",
            "emoji": "\u2728",
            "discount_percentage": 10
        },
        {
            "id": 985,
            "name": "LED Photo Frame \u2013 Illuminated and Stylish Display for Your Cherished Memories | Katyayani Creations",
            "url": "led-photoframe-",
            "brand_id": "0",
            "sku": "KCPR1985",
            "price": 750,
            "mrp": 999,
            "pprice": 320,
            "category": "Home & Decor",
            "stock": 1,
            "in_stock": true,
            "image": "https:\/\/d1s4zcjwkikclq.cloudfront.net\/main_prod_images\/KCPR1985\/KCPR1985_17125772690.jpeg",
            "emoji": "\u2728",
            "discount_percentage": 24.92
        },
        {
            "id": 1549,
            "name": "Labubu Hard Shell School Bags",
            "url": "labubu-hard-shell-school-bags",
            "brand_id": "0",
            "sku": "KCPR11549",
            "price": 396,
            "mrp": 440,
            "pprice": 220,
            "category": "Return Gift Items",
            "stock": 1,
            "in_stock": true,
            "image": "https:\/\/d1s4zcjwkikclq.cloudfront.net\/main_prod_images\/KCPR11549\/KCPR11549_17577644460.jpg",
            "emoji": "\u2728",
            "discount_percentage": 10
        },
        {
            "id": 528,
            "name": "Lagori Game (Pithu Game With Multicolored Tiles)",
            "url": "lagori-game-pithu-game-with-multicolored-tiles",
            "brand_id": "0",
            "sku": "KCPR1528",
            "price": 315,
            "mrp": 349,
            "pprice": 210,
            "category": "Toys",
            "stock": 1,
            "in_stock": true,
            "image": "https:\/\/d1s4zcjwkikclq.cloudfront.net\/main_prod_images\/KCPR1528\/1673288054.jpg",
            "emoji": "\u2728",
            "discount_percentage": 9.74
        },
        {
            "id": 570,
            "name": "Lamination",
            "url": "lamination",
            "brand_id": "0",
            "sku": "KCPR1570",
            "price": 20,
            "mrp": 20,
            "pprice": 5,
            "category": "Stationery",
            "stock": 32,
            "in_stock": true,
            "image": "https:\/\/d1s4zcjwkikclq.cloudfront.net\/main_prod_images\/KCPR1570\/1677646847.jpg",
            "emoji": "\u2728",
            "discount_percentage": 0
        },
        {
            "id": 68,
            "name": "Lantern Candle Big LED - Stylish and Practical LED Lantern for Ambient Lighting | Katyayani Creations",
            "url": "lantern-candle-big-led",
            "brand_id": "0",
            "sku": "KCPR1068",
            "price": 750,
            "mrp": 800,
            "pprice": 400,
            "category": "Diwali Items, Home & Decor, Home & Decor: Lamps, WA Diwali Items",
            "stock": 2,
            "in_stock": true,
            "image": "https:\/\/d1s4zcjwkikclq.cloudfront.net\/main_prod_images\/KCPR1068\/1661357356.jpeg",
            "emoji": "\u2728",
            "discount_percentage": 6.25
        },
        {
            "id": 1399,
            "name": "Laptop",
            "url": "laptop",
            "brand_id": "0",
            "sku": "KCPR11399",
            "price": 449,
            "mrp": 499,
            "pprice": 135,
            "category": "Toys",
            "stock": 1,
            "in_stock": true,
            "image": "https:\/\/d1s4zcjwkikclq.cloudfront.net\/main_prod_images\/KCPR11399\/KCPR11399_17581642324.jpg",
            "emoji": "\u2728",
            "discount_percentage": 10.02
        },
        {
            "id": 1269,
            "name": "Laser Light",
            "url": "laser-light",
            "brand_id": "0",
            "sku": "KCPR11269",
            "price": 50,
            "mrp": 60,
            "pprice": 25,
            "category": "Stationery",
            "stock": 6,
            "in_stock": true,
            "image": "https:\/\/d1s4zcjwkikclq.cloudfront.net\/main_prod_images\/KCPR11269\/KCPR11269_17390342970.webp",
            "emoji": "\u2728",
            "discount_percentage": 16.67
        },
        {
            "id": 1534,
            "name": "Laxmi Charan NT1800",
            "url": "laxmi-charan-nt1800",
            "brand_id": "0",
            "sku": "KCPR11534",
            "price": 135,
            "mrp": 150,
            "pprice": 60,
            "category": "Diwali Items, Home & Decor",
            "stock": 10,
            "in_stock": true,
            "image": "https:\/\/d1s4zcjwkikclq.cloudfront.net\/main_prod_images\/KCPR11534\/KCPR11534_17583664410.jpg",
            "emoji": "\u2728",
            "discount_percentage": 10
        },
        {
            "id": 934,
            "name": "Learner Study Phone KCPR1934 Online - Katyayani Creations",
            "url": "learner-study-phone",
            "brand_id": "0",
            "sku": "KCPR1934",
            "price": 360,
            "mrp": 399,
            "pprice": 175,
            "category": "Toys",
            "stock": 1,
            "in_stock": true,
            "image": "https:\/\/d1s4zcjwkikclq.cloudfront.net\/main_prod_images\/KCPR1934\/KCPR1934_17123164930.jpeg",
            "emoji": "\u2728",
            "discount_percentage": 9.77
        },
        {
            "id": 569,
            "name": "Led Lantern Diya Candle Tea Lights",
            "url": "led-lantern-diya-candle-tea",
            "brand_id": "0",
            "sku": "KCPR1569",
            "price": 600,
            "mrp": 700,
            "pprice": 312,
            "category": "Diwali Items",
            "stock": 3,
            "in_stock": true,
            "image": "https:\/\/d1s4zcjwkikclq.cloudfront.net\/main_prod_images\/KCPR1569\/1676562869.jpg",
            "emoji": "\u2728",
            "discount_percentage": 14.29
        },
        {
            "id": 924,
            "name": "Legends Avengers",
            "url": "legends",
            "brand_id": "0",
            "sku": "KCPR1924",
            "price": 180,
            "mrp": 200,
            "pprice": 75,
            "category": "Toys, Toys: Avengers",
            "stock": 4,
            "in_stock": true,
            "image": "https:\/\/d1s4zcjwkikclq.cloudfront.net\/main_prod_images\/KCPR1924\/KCPR1924_17126603180.webp",
            "emoji": "\u2728",
            "discount_percentage": 10
        },
        {
            "id": 1223,
            "name": "Lego Block Spoon & Fork Set Cutlery Set with Storage Box | 304 Stainless Steel BPA Free for Kids | Birthday Return Gift",
            "url": "lego-block-spoon-fork-set-cutlery-set-with-storage-box-304-stainless-steel-bpa-free-for-kids-birthday-return-gift",
            "brand_id": "0",
            "sku": "KCPR11223",
            "price": 202,
            "mrp": 270,
            "pprice": 135,
            "category": "Stationery, Toys",
            "stock": 2,
            "in_stock": true,
            "image": "https:\/\/d1s4zcjwkikclq.cloudfront.net\/main_prod_images\/KCPR11223\/KCPR11223_17342905555.webp",
            "emoji": "\u2728",
            "discount_percentage": 25.19
        },
        {
            "id": 783,
            "name": "Light Box",
            "url": "light-box",
            "brand_id": "0",
            "sku": "KCPR1783",
            "price": 160,
            "mrp": 200,
            "pprice": 65,
            "category": "Stationery, Stationery: Boxes",
            "stock": 1,
            "in_stock": true,
            "image": "https:\/\/d1s4zcjwkikclq.cloudfront.net\/main_prod_images\/KCPR1783\/16967047540.jpg",
            "emoji": "\u2728",
            "discount_percentage": 20
        },
        {
            "id": 1520,
            "name": "Lily Doll",
            "url": "lily-doll",
            "brand_id": "0",
            "sku": "KCPR11520",
            "price": 404,
            "mrp": 449,
            "pprice": 160,
            "category": "Toys",
            "stock": 1,
            "in_stock": true,
            "image": "",
            "emoji": "\u2728",
            "discount_percentage": 10.02
        },
        {
            "id": 1364,
            "name": "Lippan Art Handcrafted Toy - Traditional Rajasthani Mud Mirror Work for Kids",
            "url": "lippan-art",
            "brand_id": "2",
            "sku": "KCPR11364",
            "price": 675,
            "mrp": 750,
            "pprice": 375,
            "category": "Toys",
            "stock": 1,
            "in_stock": true,
            "image": "https:\/\/d1s4zcjwkikclq.cloudfront.net\/main_prod_images\/KCPR11364\/KCPR11364_17444935721.webp",
            "emoji": "\u2728",
            "discount_percentage": 10
        },
        {
            "id": 1410,
            "name": "Liquid GT Liquid Ink Pen",
            "url": "liquid-gt-liquid-ink-pen",
            "brand_id": "9",
            "sku": "KCPR11410",
            "price": 9,
            "mrp": 10,
            "pprice": 7,
            "category": "Stationery, Stationery: Pens",
            "stock": 7,
            "in_stock": true,
            "image": "https:\/\/d1s4zcjwkikclq.cloudfront.net\/main_prod_images\/KCPR11410\/KCPR11410_17474908430.webp",
            "emoji": "\u2728",
            "discount_percentage": 10
        },
        {
            "id": 868,
            "name": "Lixel IO Ball Pen \u2013 Premium Quality for a Superior Writing Experience",
            "url": "lixel-io-ball-pen",
            "brand_id": "35",
            "sku": "KCPR1868",
            "price": 9,
            "mrp": 10,
            "pprice": 5,
            "category": "Stationery, Stationery: Pens",
            "stock": 191,
            "in_stock": true,
            "image": "https:\/\/d1s4zcjwkikclq.cloudfront.net\/main_prod_images\/KCPR1868\/17021421590.jpeg",
            "emoji": "\u2728",
            "discount_percentage": 10
        },
        {
            "id": 1528,
            "name": "Lotus Latkan NT700",
            "url": "lotus-latkan-nt700",
            "brand_id": "0",
            "sku": "KCPR11528",
            "price": 630,
            "mrp": 700,
            "pprice": 240,
            "category": "Home & Decor, Diwali Items",
            "stock": 6,
            "in_stock": true,
            "image": "",
            "emoji": "\u2728",
            "discount_percentage": 10
        },
        {
            "id": 699,
            "name": "Love Colorful Water Bottle",
            "url": "love-colorful-water-bottle",
            "brand_id": "0",
            "sku": "KCPR1699",
            "price": 180,
            "mrp": 200,
            "pprice": 78,
            "category": "Return Gift Items",
            "stock": 2,
            "in_stock": true,
            "image": "https:\/\/d1s4zcjwkikclq.cloudfront.net\/main_prod_images\/KCPR1699\/1684490980.jpeg",
            "emoji": "\u2728",
            "discount_percentage": 10
        },
        {
            "id": 28,
            "name": "Love Hans (5inch)",
            "url": "love-hans-5inch",
            "brand_id": "0",
            "sku": "KCPR1028",
            "price": 250,
            "mrp": 280,
            "pprice": 60,
            "category": "Home & Decor, Home & Decor:Valentine Day Special",
            "stock": 2,
            "in_stock": true,
            "image": "https:\/\/d1s4zcjwkikclq.cloudfront.net\/main_prod_images\/KCPR1028\/PlBmOaRo.jpeg",
            "emoji": "\u2728",
            "discount_percentage": 10.71
        },
        {
            "id": 826,
            "name": "Love Mugs",
            "url": "love-mugs",
            "brand_id": "0",
            "sku": "KCPR1826",
            "price": 225,
            "mrp": 250,
            "pprice": 108,
            "category": "Return Gift Items",
            "stock": 2,
            "in_stock": true,
            "image": "https:\/\/d1s4zcjwkikclq.cloudfront.net\/main_prod_images\/KCPR1826\/16961799060.jpg",
            "emoji": "\u2728",
            "discount_percentage": 10
        },
        {
            "id": 1034,
            "name": "Lovely Angle Pcs Rattle - Colorful Baby Rattle Toy | Katyayani Creations",
            "url": "lovely-angle-pcs-rattle",
            "brand_id": "0",
            "sku": "KCPR11034",
            "price": 330,
            "mrp": 459,
            "pprice": 165,
            "category": "Toys, Toys: New Born",
            "stock": 1,
            "in_stock": true,
            "image": "https:\/\/d1s4zcjwkikclq.cloudfront.net\/main_prod_images\/KCPR11034\/KCPR11034_17125955050.jpg",
            "emoji": "\u2728",
            "discount_percentage": 28.1
        },
        {
            "id": 519,
            "name": "Lovely Angle Sweet Rattle Toy - Perfect Baby Gift | Katyayani Creations",
            "url": "lovely-angle-sweet-rattle-toy",
            "brand_id": "0",
            "sku": "KCPR1519",
            "price": 249,
            "mrp": 299,
            "pprice": 110,
            "category": "Toys, Toys: New Born",
            "stock": 2,
            "in_stock": true,
            "image": "https:\/\/d1s4zcjwkikclq.cloudfront.net\/main_prod_images\/KCPR1519\/1673258654.jpeg",
            "emoji": "\u2728",
            "discount_percentage": 16.72
        },
        {
            "id": 480,
            "name": "Ludo Snakes & Ladder & Chess",
            "url": "ludo-snakes-ladder-chess",
            "brand_id": "0",
            "sku": "KCPR1480",
            "price": 140,
            "mrp": 175,
            "pprice": 60,
            "category": "Toys, Toys: Board Games",
            "stock": 1,
            "in_stock": true,
            "image": "https:\/\/d1s4zcjwkikclq.cloudfront.net\/main_prod_images\/KCPR1480\/1672555980.jpg",
            "emoji": "\u2728",
            "discount_percentage": 20
        },
        {
            "id": 139,
            "name": "Ludo Snakes and Ladders Game Set | Katyayani Creations",
            "url": "ludo-snakes-and-ladders",
            "brand_id": "1",
            "sku": "KCPR1139",
            "price": 239,
            "mrp": 295,
            "pprice": 110,
            "category": "Toys: Board Games",
            "stock": 2,
            "in_stock": true,
            "image": "https:\/\/d1s4zcjwkikclq.cloudfront.net\/main_prod_images\/KCPR1139\/1663257490.jpeg",
            "emoji": "\u2728",
            "discount_percentage": 18.98
        },
        {
            "id": 1502,
            "name": "Ludo Yellow",
            "url": "ludo-yellow",
            "brand_id": "0",
            "sku": "KCPR11502",
            "price": 139,
            "mrp": 155,
            "pprice": 50,
            "category": "Toys",
            "stock": 2,
            "in_stock": true,
            "image": "https:\/\/d1s4zcjwkikclq.cloudfront.net\/main_prod_images\/KCPR11502\/KCPR11502_17573644160.jpg",
            "emoji": "\u2728",
            "discount_percentage": 10.32
        },
        {
            "id": 1266,
            "name": "Luxor OHP Marker",
            "url": "luxor-ohp-marker",
            "brand_id": "0",
            "sku": "KCPR11266",
            "price": 9,
            "mrp": 10,
            "pprice": 6,
            "category": "Stationery",
            "stock": 4,
            "in_stock": true,
            "image": "https:\/\/d1s4zcjwkikclq.cloudfront.net\/main_prod_images\/KCPR11266\/KCPR11266_17356429511.webp",
            "emoji": "\u2728",
            "discount_percentage": 10
        },
        {
            "id": 76,
            "name": "MIKASHU Yoga Mat",
            "url": "mikashu-yoga-mat",
            "brand_id": "0",
            "sku": "KCPR1076",
            "price": 350,
            "mrp": 375,
            "pprice": 135,
            "category": null,
            "stock": 1,
            "in_stock": true,
            "image": "https:\/\/d1s4zcjwkikclq.cloudfront.net\/main_prod_images\/KCPR1076\/mat1.webp",
            "emoji": "\u2728",
            "discount_percentage": 6.67
        },
        {
            "id": 961,
            "name": "MUG 51346",
            "url": "mug-51346",
            "brand_id": "0",
            "sku": "KCPR1961",
            "price": 225,
            "mrp": 250,
            "pprice": 95,
            "category": "Home & Decor",
            "stock": 1,
            "in_stock": true,
            "image": "",
            "emoji": "\u2728",
            "discount_percentage": 10
        },
        {
            "id": 982,
            "name": "MUG 51364",
            "url": "mug",
            "brand_id": "0",
            "sku": "KCPR1982",
            "price": 225,
            "mrp": 250,
            "pprice": 95,
            "category": "Return Gift Items",
            "stock": 2,
            "in_stock": true,
            "image": "https:\/\/d1s4zcjwkikclq.cloudfront.net\/main_prod_images\/KCPR1982\/KCPR1982_17124725100.jpg",
            "emoji": "\u2728",
            "discount_percentage": 10
        },
        {
            "id": 963,
            "name": "MUG 51372",
            "url": "mug-51372",
            "brand_id": "0",
            "sku": "KCPR1963",
            "price": 225,
            "mrp": 250,
            "pprice": 95,
            "category": "Home & Decor",
            "stock": 1,
            "in_stock": true,
            "image": "",
            "emoji": "\u2728",
            "discount_percentage": 10
        },
        {
            "id": 974,
            "name": "MUG 51373",
            "url": "mug-51373",
            "brand_id": "0",
            "sku": "KCPR1974",
            "price": 360,
            "mrp": 400,
            "pprice": 160,
            "category": "Home & Decor, Home & Decor: Crockery",
            "stock": 1,
            "in_stock": true,
            "image": "https:\/\/d1s4zcjwkikclq.cloudfront.net\/main_prod_images\/KCPR1974\/KCPR1974_17124726010.jpeg",
            "emoji": "\u2728",
            "discount_percentage": 10
        }
    ]
}