{
    "status": "success",
    "count": 6,
    "data": [
        {
            "id": 120,
            "name": "B&W Printout",
            "url": "bw-printout",
            "brand_id": "0",
            "sku": "KCPR1120",
            "price": 3,
            "mrp": 3,
            "pprice": 2,
            "category": "Prints",
            "stock": 10,
            "in_stock": true,
            "image": "",
            "emoji": "\u2728",
            "discount_percentage": 0
        },
        {
            "id": 1087,
            "name": "Mix Craft Items",
            "url": "mix-craft-items",
            "brand_id": "0",
            "sku": "KCPR11087",
            "price": 20,
            "mrp": 20,
            "pprice": 10,
            "category": "Stationery, Stationery: Craft Items",
            "stock": 474,
            "in_stock": true,
            "image": "https:\/\/d1s4zcjwkikclq.cloudfront.net\/main_prod_images\/KCPR11087\/KCPR11087_17180096210.jpg",
            "emoji": "\u2728",
            "discount_percentage": 0
        },
        {
            "id": 553,
            "name": "Multi-Colored Sparkle Glitter Powder",
            "url": "multicolored-sparkle-glitter-powder",
            "brand_id": "0",
            "sku": "KCPR1553",
            "price": 20,
            "mrp": 25,
            "pprice": 10.8,
            "category": "Stationery, Stationery: Craft Items",
            "stock": 11,
            "in_stock": true,
            "image": "https:\/\/d1s4zcjwkikclq.cloudfront.net\/main_prod_images\/KCPR1553\/1675072423.jpg",
            "emoji": "\u2728",
            "discount_percentage": 20
        },
        {
            "id": 892,
            "name": "Photo Paper Printout",
            "url": "photo-paper-printout",
            "brand_id": "0",
            "sku": "KCPR1892",
            "price": 20,
            "mrp": 20,
            "pprice": 4,
            "category": "Prints",
            "stock": 104,
            "in_stock": true,
            "image": "",
            "emoji": "\u2728",
            "discount_percentage": 0
        },
        {
            "id": 893,
            "name": "Sticky Notes",
            "url": "sticky-notes",
            "brand_id": "36",
            "sku": "KCPR1893",
            "price": 36,
            "mrp": 40,
            "pprice": 20,
            "category": "Stationery",
            "stock": 6,
            "in_stock": true,
            "image": "https:\/\/d1s4zcjwkikclq.cloudfront.net\/main_prod_images\/KCPR1893\/17076651570.jpg",
            "emoji": "\u2728",
            "discount_percentage": 10
        },
        {
            "id": 875,
            "name": "World Map",
            "url": "world-map",
            "brand_id": "0",
            "sku": "KCPR1875",
            "price": 1,
            "mrp": 2,
            "pprice": 0.5,
            "category": "Stationery",
            "stock": 113,
            "in_stock": true,
            "image": "https:\/\/d1s4zcjwkikclq.cloudfront.net\/main_prod_images\/KCPR1875\/17028127130.jpg",
            "emoji": "\u2728",
            "discount_percentage": 50
        }
    ]
}